bsi_sentiment/__init__.py
bsi_sentiment/bsi_sentiment.py
bsi_sentiment/parser.py
bsi_sentiment/twitter.py
bsi_sentiment/utils.py
tests/__init__.py
tests/bsi_sentiment_test.py
bsi_sentiment-0.1.0.dist-info/LICENSE
bsi_sentiment-0.1.0.dist-info/METADATA
bsi_sentiment-0.1.0.dist-info/WHEEL
bsi_sentiment-0.1.0.dist-info/entry_points.txt
bsi_sentiment-0.1.0.dist-info/top_level.txt
bsi_sentiment-0.1.0.dist-info/RECORD
