Metadata-Version: 2.1
Name: bsi-sentiment
Version: 0.1.0
Summary: BSI Tool for Sentiment Analysis
Home-page: https://github.com/BSI-Bocconi/bsi-sentiment
Author: Stefano Cortinovis, Pietro Domietto, Elio Scarci, Kasra Zamanian
Author-email: scortino@pm.me
Classifier: Development Status :: 3 - Alpha
Classifier: Intended Audience :: Developers
Classifier: License :: OSI Approved :: GNU General Public License v3 (GPLv3)
Classifier: Natural Language :: English
Classifier: Operating System :: OS Independent
Classifier: Programming Language :: Python :: 3
Requires-Python: >=3.6
License-File: LICENSE
Requires-Dist: nltk (~=3.7)
Requires-Dist: snscrape (~=0.4.3.20220106)
Requires-Dist: textblob (~=0.17.1)
Requires-Dist: tqdm (~=4.62.3)
Requires-Dist: tweepy (~=4.9.0)
